anu_ctlab_io/__init__.py
anu_ctlab_io/_dataset.py
anu_ctlab_io/_datatype.py
anu_ctlab_io/_parse_history.py
anu_ctlab_io/_version.py
anu_ctlab_io/_voxel_properties.py
anu_ctlab_io/py.typed
anu_ctlab_io/netcdf/__init__.py
anu_ctlab_io/zarr/__init__.py
anu_ctlab_io-1.1.0.dist-info/METADATA
anu_ctlab_io-1.1.0.dist-info/WHEEL
anu_ctlab_io-1.1.0.dist-info/licenses/LICENSE.md
anu_ctlab_io-1.1.0.dist-info/RECORD
